rockcaptcha/__init__.py
rockcaptcha/exeptions.py
rockcaptcha/helpers.py
rockcaptcha-1.0.2.dist-info/METADATA
rockcaptcha-1.0.2.dist-info/WHEEL
rockcaptcha-1.0.2.dist-info/RECORD
