Metadata-Version: 2.1
Name: rockcaptcha
Version: 1.0.2
Summary: Rockcaptcha solve recaptchaV2, recaptchaV3, funcaptcha, imageToText very fast and cheap
Home-page: https://rockcaptcha.com
License: MIT
Keywords: rockcaptcha,recaptcha,recaptchav3,funcaptcha,imagetotext,solver captcha,recaptcha solver,funcaptcha solver,recaptcha recognition
Author: Rockcaptcha
Author-email: support@rockcaptcha.com
Requires-Python: >=3.7,<4.0
Classifier: License :: OSI Approved :: MIT License
Classifier: Programming Language :: Python :: 3
Classifier: Programming Language :: Python :: 3.7
Classifier: Programming Language :: Python :: 3.8
Classifier: Programming Language :: Python :: 3.9
Classifier: Programming Language :: Python :: 3.10
Classifier: Programming Language :: Python :: 3.11
Requires-Dist: requests (>=2.31.0,<3.0.0)
